trulie/__init__.py
trulie/tableau.py
trulie/version.py
trulie-0.1.0.dist-info/LICENSE
trulie-0.1.0.dist-info/METADATA
trulie-0.1.0.dist-info/WHEEL
trulie-0.1.0.dist-info/top_level.txt
trulie-0.1.0.dist-info/RECORD
